shell_utils/__init__.py
shell_utils/cli.py
shell_utils/notify.py
shell_utils/runner.py
shell_utils/shell_utils.py
shell_utils-2.3.1.dist-info/entry_points.txt
shell_utils-2.3.1.dist-info/LICENSE
shell_utils-2.3.1.dist-info/WHEEL
shell_utils-2.3.1.dist-info/METADATA
shell_utils-2.3.1.dist-info/RECORD
