Metadata-Version: 2.1
Name: shell-utils
Version: 2.3.1
Summary: Shell automation tools, like Make on steroids.
Home-page: https://github.com/knowsuchagency/shell-utils
License: BSD-4-Clause
Author: Stephan Fitzpatrick
Author-email: knowsuchagency@gmail.com
Classifier: License :: Other/Proprietary License
Classifier: Programming Language :: Python :: 2
Classifier: Programming Language :: Python :: 2.7
Classifier: Programming Language :: Python :: 3
Classifier: Programming Language :: Python :: 3.4
Classifier: Programming Language :: Python :: 3.5
Classifier: Programming Language :: Python :: 3.6
Classifier: Programming Language :: Python :: 3.7
Requires-Dist: click (>=6.7,<7.0)
